coda/__init__.py
coda/doisearch/__init__.py
coda/doisearch/_json.py
coda/doisearch/crossref.py
coda/py.typed
coda_doisearch-0.2.0.dist-info/METADATA
coda_doisearch-0.2.0.dist-info/WHEEL
coda_doisearch-0.2.0.dist-info/licenses/LICENSE
coda_doisearch-0.2.0.dist-info/RECORD
